googletrans/__init__.py
googletrans/client.py
googletrans/constants.py
googletrans/gtoken.py
googletrans/models.py
googletrans/urls.py
googletrans/utils.py
googletrans_sw-4.0.0.dist-info/METADATA
googletrans_sw-4.0.0.dist-info/WHEEL
googletrans_sw-4.0.0.dist-info/top_level.txt
googletrans_sw-4.0.0.dist-info/RECORD
